itomate/__init__.py
itomate/itomate.py
itomate-0.3.9.dist-info/METADATA
itomate-0.3.9.dist-info/WHEEL
itomate-0.3.9.dist-info/entry_points.txt
itomate-0.3.9.dist-info/top_level.txt
itomate-0.3.9.dist-info/RECORD
